cli/__init__.py
cli/check.py
cli/cli.py
cli/organize_files.py
opfo_cli/__init__.py
opfo_cli/__main__.py
util/__init__.py
util/config_obj.py
util/get_logger.py
util/is_hidden.py
opfo-1.0.1.dist-info/METADATA
opfo-1.0.1.dist-info/WHEEL
opfo-1.0.1.dist-info/entry_points.txt
opfo-1.0.1.dist-info/top_level.txt
opfo-1.0.1.dist-info/RECORD
