Metadata-Version: 2.4
Name: opfo
Version: 1.0.1
Summary: opfo OverPowerdFileOrganizer is an advanced file organizer implemented in python
Maintainer-email: Omar Arabi <omarbuisness7@gmail.com>
Requires-Python: >=3.13
Requires-Dist: loguru>=0.7.3
